{
    "common": {
        "name": "viessmannapi",
        "version": "1.1.2",
        "news": {
            "1.1.2": {
                "en": "Fixed bug: email & password were not removed from config in existing installations",
                "de": "Bugfix: email & password wurden in bestehenden Installationen nicht aus config entfernt"
            },
            "1.1.1": {
                "en": "Fixed a bug preventing certain properties from beeing exposed as state",
                "de": "Bugfix: manche Properties wurden nicht als state exportiert"
            },
            "1.1.0": {
                "en": "No longer stores email and password if initial connection was sucessful",
                "de": "Email und Password werden nicht mehr gespeichert wenn die Verbindung erstmalig erfolgreich hergestellt wurde"
            },
            "1.0.0": {
                "en": "Initial version - requests data from the viessmann server and writes it into states",
                "de": "Initiale Version - Fragt Daten über den Viessmann Server ab und speichert sie in entsprechenden states"
            }
        },
        "title": "Viessmann API Adapter",
        "titleLang": {
            "en": "Viessmann API Adapter",
            "de": "Viessmann API Adapter"
        },
        "desc": {
            "en": "Adapter to communicate with a Viessmann heating system via the API used by Viessmann Apps",
            "de": "Adapter um mit einer Viessmann Heizung über die von den Viessmann Apps genutzte API zu kommunizieren"
        },
        "authors": [
            "Thomas Vidic <theuklid@gmail.com>"
        ],
        "docs": {
            "en": "docs/en/admin.md",
            "de": "docs/de/admin.md"
        },
        "platform": "Javascript/Node.js",
        "mode": "daemon",
        "icon": "viessmannapi.png",
        "materialize": true,
        "enabled": true,
        "extIcon": "https://raw.githubusercontent.com/thovid/ioBroker.viessmannapi/master/admin/viessmannapi.png",
        "keywords": [
            "viessmann", "api", "heating"
        ],
        "readme": "https://github.com/thovid/ioBroker.viessmannapi/blob/master/README.md",
        "loglevel": "info",
        "type": "general",
        "license": "MIT",
        "messagebox": false
    },
    "native": {
        "email": "",
        "password": ""
    },
    "objects": []
}